<?xml version="1.0" encoding="UTF-8"?>

<!-- generated on 2024-12-29 02:03:51 by Eclipse SUMO GUI Version 1.19.0
<configuration xmlns:xsi="http://www.w3.org/2001/XMLSchema-instance" xsi:noNamespaceSchemaLocation="http://sumo.dlr.de/xsd/sumoConfiguration.xsd">

    <input>
        <net-file value="D:\sumo\.project\openstreetmap\2map.net.xml"/>
        <route-files value="D:\sumo\.project\openstreetmap\routes.rou.xml"/>
        <additional-files value="D:\sumo\.project\openstreetmap\MenJiaWeiZhi.add.xml"/>
    </input>

    <output>
        <fcd-output value="D:\sumo\.project\openstreetmap\fcd-output.xml"/>
    </output>

    <time>
        <begin value="0"/>
        <end value="3600"/>
    </time>

    <gui_only>
        <quit-on-end value="t"/>
        <start value="t"/>
    </gui_only>

</configuration>
-->

<detector xmlns:xsi="http://www.w3.org/2001/XMLSchema-instance" xsi:noNamespaceSchemaLocation="http://sumo.dlr.de/xsd/det_e1_file.xsd">
    <interval begin="0.00" end="300.00" id="SK682-2" nVehContrib="62" flow="744.00" occupancy="2.78" speed="37.41" harmonicMeanSpeed="37.21" length="5.00" nVehEntered="62"/>
    <interval begin="300.00" end="600.00" id="SK682-2" nVehContrib="56" flow="672.00" occupancy="2.47" speed="37.92" harmonicMeanSpeed="37.81" length="5.00" nVehEntered="56"/>
    <interval begin="600.00" end="900.00" id="SK682-2" nVehContrib="49" flow="588.00" occupancy="2.21" speed="37.12" harmonicMeanSpeed="36.90" length="5.00" nVehEntered="49"/>
    <interval begin="900.00" end="1200.00" id="SK682-2" nVehContrib="59" flow="708.00" occupancy="2.61" speed="37.85" harmonicMeanSpeed="37.71" length="5.00" nVehEntered="59"/>
    <interval begin="1200.00" end="1500.00" id="SK682-2" nVehContrib="54" flow="648.00" occupancy="2.43" speed="37.31" harmonicMeanSpeed="37.10" length="5.00" nVehEntered="54"/>
    <interval begin="1500.00" end="1800.00" id="SK682-2" nVehContrib="49" flow="588.00" occupancy="2.21" speed="37.11" harmonicMeanSpeed="36.93" length="5.00" nVehEntered="49"/>
    <interval begin="1800.00" end="2100.00" id="SK682-2" nVehContrib="51" flow="612.00" occupancy="2.26" speed="37.74" harmonicMeanSpeed="37.61" length="5.00" nVehEntered="51"/>
    <interval begin="2100.00" end="2400.00" id="SK682-2" nVehContrib="50" flow="600.00" occupancy="2.25" speed="37.27" harmonicMeanSpeed="37.11" length="5.00" nVehEntered="50"/>
    <interval begin="2400.00" end="2700.00" id="SK682-2" nVehContrib="47" flow="564.00" occupancy="2.10" speed="37.52" harmonicMeanSpeed="37.35" length="5.00" nVehEntered="47"/>
    <interval begin="2700.00" end="3000.00" id="SK682-2" nVehContrib="55" flow="660.00" occupancy="2.47" speed="37.31" harmonicMeanSpeed="37.11" length="5.00" nVehEntered="55"/>
    <interval begin="3000.00" end="3300.00" id="SK682-2" nVehContrib="53" flow="636.00" occupancy="2.40" speed="37.03" harmonicMeanSpeed="36.84" length="5.00" nVehEntered="53"/>
    <interval begin="3300.00" end="3600.00" id="SK682-2" nVehContrib="51" flow="612.00" occupancy="2.27" speed="37.59" harmonicMeanSpeed="37.41" length="5.00" nVehEntered="51"/>
</detector>
